<annotation>
	<folder>JPEGImages</folder>
	<filename>2012_004002.jpg</filename>
	<path>/home/sidorela/Downloads/PascalVOC2012/VOC2012/JPEGImages/2012_004002.jpg</path>
	<source>
		<database>Unknown</database>
	</source>
	<size>
		<width>500</width>
		<height>375</height>
		<depth>3</depth>
	</size>
	<segmented>0</segmented>
	<object>
		<name>person</name>
		<pose>Unspecified</pose>
		<truncated>1</truncated>
		<difficult>0</difficult>
		<bndbox>
			<xmin>332</xmin>
			<ymin>27</ymin>
			<xmax>468</xmax>
			<ymax>375</ymax>
		</bndbox>
	</object>
	<object>
		<name>person</name>
		<pose>Unspecified</pose>
		<truncated>0</truncated>
		<difficult>0</difficult>
		<bndbox>
			<xmin>23</xmin>
			<ymin>155</ymin>
			<xmax>200</xmax>
			<ymax>368</ymax>
		</bndbox>
	</object>
	<object>
		<name>person</name>
		<pose>Unspecified</pose>
		<truncated>0</truncated>
		<difficult>0</difficult>
		<bndbox>
			<xmin>11</xmin>
			<ymin>165</ymin>
			<xmax>63</xmax>
			<ymax>275</ymax>
		</bndbox>
	</object>
</annotation>
